osirixgrpc/.gitignore
osirixgrpc/README.md
osirixgrpc/__init__.py
osirixgrpc/browsercontroller_pb2.py
osirixgrpc/dcmpix_pb2.py
osirixgrpc/dicomimage_pb2.py
osirixgrpc/dicomseries_pb2.py
osirixgrpc/dicomstudy_pb2.py
osirixgrpc/osirix_pb2.py
osirixgrpc/osirix_pb2_grpc.py
osirixgrpc/roi_pb2.py
osirixgrpc/roivolume_pb2.py
osirixgrpc/types_pb2.py
osirixgrpc/utilities_pb2.py
osirixgrpc/viewercontroller_pb2.py
osirixgrpc/vrcontroller_pb2.py
osirixgrpc-0.2.1b6.dist-info/METADATA
osirixgrpc-0.2.1b6.dist-info/WHEEL
osirixgrpc-0.2.1b6.dist-info/licenses/LICENSE.txt
osirixgrpc-0.2.1b6.dist-info/RECORD
