Metadata-Version: 2.4
Name: osirixgrpc
Version: 0.2.1b6
Summary: gRPC interface for interacting with OsiriX
Project-URL: Homepage, https://osirixgrpc.github.io/osirixgrpc/
Project-URL: Documentation, https://osirixgrpc.github.io/osirixgrpc/
Project-URL: Repository, https://github.com/osirixgrpc/osirixgrpc
Project-URL: Bug Tracker, https://github.com/osirixgrpc/osirixgrpc/issues
Author-email: Matthew D Blackledge <mattyblackledge@gmail.com>, Timothy Sum Hon Mun <timothy22000@gmail.com>, Richard Holbrey <richard.holbrey@icr.ac.uk>
Maintainer-email: Matthew D Blackledge <mattyblackledge@gmail.com>
License: Copyright (c) 2024 Matthew D Blackledge, Timothy Sum Hon Mun, and The Institute of Cancer Research
License-File: LICENSE.txt
Keywords: Artificial Intelligence,Dicom,Image Processing,Medical Imaging
Classifier: Development Status :: 3 - Alpha
Classifier: License :: OSI Approved :: MIT License
Classifier: Natural Language :: English
Classifier: Operating System :: MacOS :: MacOS X
Classifier: Programming Language :: Python :: 3
Requires-Python: >=3.8
Requires-Dist: grpcio-tools>=1.55.0
Requires-Dist: grpcio>=1.55.0
